README.md
setup.cfg
setup.py
elmicpy/__init__.py
elmicpy/config.py
elmicpy.egg-info/PKG-INFO
elmicpy.egg-info/SOURCES.txt
elmicpy.egg-info/dependency_links.txt
elmicpy.egg-info/not-zip-safe
elmicpy.egg-info/top_level.txt
test/testinstall.py