Metadata-Version: 1.0
Name: elmicpy
Version: 1.0
Summary: This module needs for make microservices elitem assistents
Home-page: UNKNOWN
Author: leomaxwell
Author-email: java.leon@mail.ru
License: MIT
Platform: UNKNOWN
